README.md
setup.py
ftir/ftir_rename
ftir/renamer.py
ftir_renamer.egg-info/PKG-INFO
ftir_renamer.egg-info/SOURCES.txt
ftir_renamer.egg-info/dependency_links.txt
ftir_renamer.egg-info/requires.txt
ftir_renamer.egg-info/top_level.txt