Metadata-Version: 2.1
Name: ftir-renamer
Version: 0.7
Summary: File renamer for FTIR files
Home-page: https://github.com/adamkoziol/ftir_renamer.git
Author: Adam Koziol
Author-email: adam.koziol@canada.ca
License: MIT
Platform: UNKNOWN
